[
	{
		"title": "SvelteKit Authentication Example",
		"url": "https://github.com/nstuyvesant/sveltekit-auth-example",
		"description": "Fully documented example of how to setup local and \"Sign in with Google\" authentication (including Google One-Tap) using PostgreSQL, signup, page authorization, user profile management and password reset using SendGrid.",
		"npm": "sveltekit-auth-example",
		"addedOn": "2022-11-16",
		"category": "SvelteKit",
		"tags": ["templates", "database", "integrations", "ssr", "typescript"]
	},
	{
		"title": "CMSvelte",
		"url": "https://github.com/sawyerclick/CMSvelte",
		"description": "A Svelte template built with newsroom CMS's in mind",
		"npm": "",
		"addedOn": "2022-02-27",
		"category": "Svelte",
		"tags": ["templates", "blog"]
	},
	{
		"addedOn": "2020-09-29T14:39:13Z",
		"category": "Svelte",
		"description": "Boilerplate with TypeScript, Webpack, Storybook, Travis CI, SCSS, Babel, EsLint, Prettier, Jest",
		"tags": [],
		"title": "agusID/boilerplate-svelte",
		"url": "https://github.com/agusID/boilerplate-svelte"
	},
	{
		"addedOn": "2020-09-29T14:39:13Z",
		"category": "Svelte",
		"description": "An example repo of a Svelte app that is IE11 compatible",
		"tags": [],
		"title": "benjazehr/svelte-example-museums",
		"url": "https://github.com/benjazehr/svelte-example-museums"
	},
	{
		"addedOn": "2020-09-29T14:39:13Z",
		"category": "Svelte",
		"description": "A truffle box for Svelte, a seed for building an Ethereum dapp using Truffle",
		"tags": [],
		"title": "antony/svelte-box",
		"url": "https://github.com/antony/svelte-box"
	},
	{
		"addedOn": "2020-09-29T14:39:13Z",
		"category": "Svelte",
		"description": "Typescript template for Svelte v3",
		"tags": [],
		"title": "Axelen123/svelte-ts-template",
		"url": "https://github.com/Axelen123/svelte-ts-template"
	},
	{
		"addedOn": "2020-09-29T14:39:13Z",
		"category": "Svelte",
		"description": "A complete implementation with components, store, unit e2e tests and linting.",
		"tags": [],
		"title": "TodoMVC Svelte",
		"url": "https://github.com/vuesomedev/todomvc-svelte"
	},
	{
		"addedOn": "2020-09-29T14:39:13Z",
		"category": "Svelte",
		"description": "Electron Svelte boilerplate",
		"tags": ["electron"],
		"title": "Blade67/Sveltron",
		"url": "https://github.com/Blade67/Sveltron"
	},
	{
		"addedOn": "2020-09-29T14:39:13Z",
		"category": "Svelte",
		"description": "A template to create multi-page application powered by Webpack",
		"tags": [],
		"title": "brandonxiang/svelte-webpack-mpa",
		"url": "https://github.com/brandonxiang/svelte-webpack-mpa"
	},
	{
		"addedOn": "2020-09-29T14:39:13Z",
		"category": "Svelte",
		"description": "Minimal boilerplate example of Svelte with Typescript using Parcel. This also includes scss support",
		"tags": [],
		"title": "dafn/svelte-typescript-parcel",
		"url": "https://github.com/dafn/svelte-typescript-parcel"
	},
	{
		"addedOn": "2020-09-29T14:39:13Z",
		"category": "Svelte",
		"description": "Minimal boilerplate example of Svelte with Typescript using Rollup. This also includes scss support",
		"tags": [],
		"title": "dafn/svelte-typescript-rollup",
		"url": "https://github.com/dafn/svelte-typescript-rollup"
	},
	{
		"addedOn": "2020-09-29T14:39:13Z",
		"category": "Svelte",
		"description": "Typescript + Storybook + Webpack boilerplate",
		"tags": [],
		"title": "farhan2106/svelte-typescript",
		"url": "https://github.com/farhan2106/svelte-typescript"
	},
	{
		"addedOn": "2020-09-29T14:39:13Z",
		"category": "Svelte",
		"description": "Starter for Svelte 3/rollup/typescript/vscode",
		"tags": [],
		"title": "geakstr/svelte-3-rollup-typescript-vscode",
		"url": "https://github.com/geakstr/svelte-3-rollup-typescript-vscode"
	},
	{
		"addedOn": "2020-09-29T14:39:13Z",
		"category": "Svelte",
		"description": "A small starter template to get up and running with Svelte v3",
		"tags": [],
		"title": "bholmesdev/svelte-starter-template",
		"url": "https://github.com/bholmesdev/svelte-starter-template"
	},
	{
		"addedOn": "2020-09-29T14:39:13Z",
		"category": "Svelte",
		"description": "The open-source storefront for any eCommerce. Built with a PWA and headless approach, using a modern JS stack. The API approach also allows you to merge Svelte Commerce with any third-party tool like payment gateways, POS or AI. WIP for MedusaJS, Woocommerce, Bigcommerce and Shopify.",
		"tags": [],
		"title": "svelte-commerce",
		"url": "https://github.com/itswadesh/svelte-commerce"
	},
	{
		"addedOn": "2020-09-29T14:39:13Z",
		"category": "Svelte",
		"description": "Svelte + Storybook + Tailwind - Starter Template",
		"tags": [],
		"title": "jerriclynsjohn/svelte-storybook-tailwind",
		"url": "https://github.com/jerriclynsjohn/svelte-storybook-tailwind"
	},
	{
		"addedOn": "2020-09-29T14:39:13Z",
		"category": "Svelte",
		"description": "A template to help you start developing SPAs with Svelte and Firebase",
		"tags": [],
		"title": "jorgegorka/svelte-firebase",
		"url": "https://github.com/jorgegorka/svelte-firebase"
	},
	{
		"addedOn": "2020-09-29T14:39:13Z",
		"category": "Svelte",
		"description": "Tailwindcss v1 + Svelte v3 = <3",
		"tags": [],
		"title": "marcograhl/tailwindcss-svelte-starter",
		"url": "https://github.com/marcograhl/tailwindcss-svelte-starter"
	},
	{
		"addedOn": "2020-09-29T14:39:13Z",
		"category": "Svelte",
		"description": "Build cybernetically enhanced web apps with Meteor and Svelte",
		"tags": ["components and libraries", "stores and state"],
		"title": "Svelte for Meteor",
		"url": "https://github.com/meteor-svelte/meteor-svelte"
	},
	{
		"addedOn": "2020-09-29T14:39:13Z",
		"category": "Svelte",
		"description": "Svelte + Tailwind = â¤",
		"tags": [],
		"title": "muhajirdev/svelte-tailwind-template",
		"url": "https://github.com/muhajirdev/svelte-tailwind-template"
	},
	{
		"addedOn": "2020-09-29T14:39:13Z",
		"category": "Svelte",
		"description": "Offline-Capable todo list built with Svelte, PouchDB and CouchDB",
		"tags": [],
		"title": "neighbourhoodie/svelte-pouchdb-couchdb",
		"url": "https://github.com/neighbourhoodie/svelte-pouchdb-couchdb"
	},
	{
		"addedOn": "2020-09-29T14:39:13Z",
		"category": "Svelte",
		"description": "Template with Typescript, Sass, Storybook, Webpack",
		"tags": [],
		"title": "ryburn52/svelte-typescript-sass-template",
		"url": "https://github.com/ryburn52/svelte-typescript-sass-template"
	},
	{
		"addedOn": "2020-09-29T14:39:13Z",
		"category": "Svelte",
		"description": "Starter to built Electron apps with Svelte and Better SQLite3",
		"tags": ["electron", "database"],
		"title": "nye/svelte-electron-better-sqlite3-starter",
		"url": "https://github.com/nye/svelte-electron-better-sqlite3-starter"
	},
	{
		"addedOn": "2020-09-29T14:39:13Z",
		"category": "Svelte",
		"description": "Svelte webpack template with routing and lazy-loading",
		"tags": [],
		"title": "OrdinaryJellyfish/svelte-routing-template",
		"url": "https://github.com/OrdinaryJellyfish/svelte-routing-template"
	},
	{
		"addedOn": "2020-09-29T14:39:13Z",
		"category": "Svelte",
		"description": "Svelte application boilerplate with Webpack, Sass, BabelJS, Fetch, PostCSS, Jest, and .Env",
		"tags": [],
		"title": "pankod/svelte-boilerplate",
		"url": "https://github.com/pankod/svelte-boilerplate"
	},
	{
		"addedOn": "2020-09-29T14:39:13Z",
		"category": "Svelte",
		"description": "A base for building Svelte component library",
		"tags": [],
		"title": "patoi/svelte-component-library-template",
		"url": "https://github.com/patoi/svelte-component-library-template"
	},
	{
		"addedOn": "2020-09-29T14:39:13Z",
		"category": "Svelte",
		"description": "Typescript monorepo for Svelte v3 (preprocess, template, types)",
		"tags": [],
		"title": "pyoner/svelte-typescript",
		"url": "https://github.com/pyoner/svelte-typescript"
	},
	{
		"addedOn": "2020-09-29T14:39:13Z",
		"category": "Svelte",
		"description": "Typescript monorepo for Svelte v3 (preprocess, template, types)",
		"npm": "@pyoner/svelte-ts-preprocess",
		"tags": ["integrations", "preprocessors"],
		"title": "@pyoner/svelte-ts-preprocess",
		"url": "https://github.com/pyoner/svelte-typescript"
	},
	{
		"addedOn": "2020-09-29T14:39:13Z",
		"category": "Svelte",
		"description": "Svelte App with Firebase Authentication for all purposes",
		"tags": [],
		"title": "ricalamino/svelte-firebase-auth",
		"url": "https://github.com/ricalamino/svelte-firebase-auth"
	},
	{
		"addedOn": "2020-09-29T14:39:13Z",
		"category": "Svelte",
		"description": "A template for building Electron apps with Svelte (**VERSION 2**)",
		"tags": ["electron"],
		"title": "Rich-Harris/svelte-template-electron",
		"url": "https://github.com/Rich-Harris/svelte-template-electron"
	},
	{
		"addedOn": "2020-09-29T14:39:13Z",
		"category": "Svelte",
		"description": "Clone of official Svelte template with added HMR support using Nollup",
		"tags": [],
		"title": "rixo/svelte-template-hot",
		"url": "https://github.com/rixo/svelte-template-hot"
	},
	{
		"addedOn": "2020-09-29T14:39:13Z",
		"category": "Svelte",
		"description": "Yeoman generator generating a boilerplate Svelte.js app with all of svelte-preprocess' options",
		"npm": "generator-svelte",
		"tags": ["preprocessors"],
		"title": "generator-svelte",
		"url": "https://github.com/Samuel-Martineau/generator-svelte"
	},
	{
		"addedOn": "2020-09-29T14:39:13Z",
		"category": "Svelte",
		"description": "A boilerplate with Material, Babel, PostCSS, and Webpack",
		"tags": [],
		"title": "Shyam-Chen/Svelte-Starter",
		"url": "https://github.com/Shyam-Chen/Svelte-Starter"
	},
	{
		"addedOn": "2020-09-29T14:39:13Z",
		"category": "Svelte",
		"description": "Boilerplate with Webpack, Cypress, Travis CI, Storybook, and SASS",
		"tags": [],
		"title": "stephanepericat/svelte-boilerplate",
		"url": "https://github.com/stephanepericat/svelte-boilerplate"
	},
	{
		"addedOn": "2020-09-29T14:39:13Z",
		"category": "Svelte",
		"description": "A base for building shareable Svelte components",
		"tags": [],
		"title": "sveltejs/component-template",
		"url": "https://github.com/sveltejs/component-template"
	},
	{
		"addedOn": "2020-09-29T14:39:13Z",
		"category": "Svelte",
		"description": "Template for building basic applications with Svelte with rollup",
		"tags": [],
		"title": "sveltejs/template",
		"url": "https://github.com/sveltejs/template"
	},
	{
		"addedOn": "2020-09-29T14:39:13Z",
		"category": "Svelte",
		"description": "Template for building basic applications with Svelte and custom elements",
		"tags": [],
		"title": "sveltejs/template-custom-element",
		"url": "https://github.com/sveltejs/template-custom-element"
	},
	{
		"addedOn": "2020-09-29T14:39:13Z",
		"category": "Svelte",
		"description": "Template for building basic Svelte applications with webpack",
		"tags": [],
		"title": "sveltejs/template-webpack",
		"url": "https://github.com/sveltejs/template-webpack"
	},
	{
		"addedOn": "2020-09-29T14:39:13Z",
		"category": "Svelte",
		"description": "Starter template for Cordova featuring hot reload",
		"tags": ["mobile"],
		"title": "syonip/svelte-cordova",
		"url": "https://github.com/syonip/svelte-cordova"
	},
	{
		"addedOn": "2020-09-29T14:39:13Z",
		"category": "Svelte",
		"description": "A showcase app for all Ionic UI elements to create awesome mobile apps. Published as web app too.",
		"tags": ["components and libraries", "component sets", "mobile"],
		"title": "Ionic Svelte UI demo",
		"url": "https://github.com/Tommertom/svelte-ionic-app"
	},
	{
		"addedOn": "2020-09-29T14:39:13Z",
		"category": "Svelte",
		"description": "A base for building shareable Svelte 3 components",
		"tags": [],
		"title": "YogliB/svelte-component-template",
		"url": "https://github.com/YogliB/svelte-component-template"
	},
	{
		"addedOn": "2020-09-29T14:39:13Z",
		"category": "Svelte",
		"description": "A base for building shareable Svelte 3 components.",
		"tags": [],
		"title": "svelte-component-template",
		"url": "https://github.com/YogliB/svelte-component-template"
	},
	{
		"addedOn": "2021-06-24T14:39:13Z",
		"category": "SvelteKit",
		"description": "SvelteKit template with TailwindCSS, Storybook, TypeScript and Sass.",
		"tags": [],
		"title": "tejasag/sveltetron-9000",
		"url": "https://github.com/tejasag/sveltetron-9000"
	},
	{
		"addedOn": "2021-06-24T14:39:14Z",
		"category": "SvelteKit",
		"description": "SvelteKit Starter template with Typescript, Postcss, scss, TailwindCSS, Storybook, husky, and eslint.",
		"tags": ["blog", "seo", "ssr", "storybook", "templates"],
		"title": "navneetsharmaui/sveltekit-starter",
		"url": "https://github.com/navneetsharmaui/sveltekit-starter"
	},
	{
		"addedOn": "2021-09-07T14:39:14Z",
		"category": "SvelteKit",
		"description": "SvelteKit Blog Starter template with Typescript, Postcss, scss, TailwindCSS, Storybook, husky, and eslint. The template is free to use and developers are welcome to contribute to it.",
		"tags": ["blog", "mdsvex", "seo", "ssr", "storybook", "templates"],
		"title": "navneetsharmaui/sveltekit-blog",
		"url": "https://github.com/navneetsharmaui/sveltekit-blog"
	},
	{
		"addedOn": "2021-06-24T14:39:16Z",
		"category": "SvelteKit",
		"description": "SvelteKit template with Stripe Checkout and Typescript.",
		"tags": [],
		"title": "srmullen/sveltekit-stripe",
		"url": "https://github.com/srmullen/sveltekit-stripe"
	},
	{
		"addedOn": "2021-06-24T14:39:17Z",
		"category": "SvelteKit",
		"description": "A minimalistic blog template built with SvelteKit and MDsveX",
		"tags": [],
		"title": "mvasigh/sveltekit-mdsvex-blog",
		"url": "https://github.com/mvasigh/sveltekit-mdsvex-blog"
	},
	{
		"addedOn": "2021-06-24T14:39:21Z",
		"category": "Svelte Add",
		"description": "Add PostCSS to your Svelte project",
		"tags": [],
		"title": "svelte-add/postcss",
		"url": "https://github.com/svelte-add/postcss"
	},
	{
		"addedOn": "2021-06-24T14:39:22Z",
		"category": "Svelte Add",
		"description": "Add Tailwind CSS to your Svelte project",
		"tags": [],
		"title": "svelte-add/tailwindcss",
		"url": "https://github.com/svelte-add/tailwindcss"
	},
	{
		"addedOn": "2023-06-01",
		"category": "Svelte Add",
		"description": "Add Tauri to your Svelte project",
		"tags": [],
		"title": "svelte-add/tauri",
		"url": "https://github.com/svelte-add/tauri"
	},
	{
		"addedOn": "2021-06-24T14:39:23Z",
		"category": "Svelte Add",
		"description": "Add Bulma to your Svelte project",
		"tags": [],
		"title": "svelte-add/bulma",
		"url": "https://github.com/svelte-add/bulma"
	},
	{
		"addedOn": "2021-06-24T14:39:24Z",
		"category": "Svelte Add",
		"description": "Add CoffeeScript to your Svelte project",
		"tags": [],
		"title": "svelte-add/coffeescript",
		"url": "https://github.com/svelte-add/coffeescript"
	},
	{
		"addedOn": "2021-06-24T14:39:26Z",
		"category": "Svelte Add",
		"description": "A command to add a GraphQL server to your Svelte project",
		"tags": [],
		"title": "svelte-add/graphql-server",
		"url": "https://github.com/svelte-add/graphql-server"
	},
	{
		"addedOn": "2021-06-24T14:39:27Z",
		"category": "Svelte Add",
		"description": "A command to add hosting on Firebase to your Svelte project",
		"tags": [],
		"title": "svelte-add/firebase-hosting",
		"url": "https://github.com/svelte-add/firebase-hosting"
	},
	{
		"title": "svelte-add/scss",
		"url": "https://github.com/svelte-add/scss",
		"description": "Add SCSS to your Svelte project",
		"tags": [],
		"addedOn": "2023-06-01",
		"category": "Svelte Add"
	},
	{
		"title": "svelte-add/3d",
		"url": "https://github.com/svelte-add/3d",
		"description": "Add 3D scenes to your Svelte project",
		"tags": [],
		"addedOn": "2023-06-01",
		"category": "Svelte Add"
	},
	{
		"title": "vhscom/svelte-headlessui-starter",
		"url": "https://github.com/vhscom/svelte-headlessui-starter",
		"description": "Template designed to make it faster and easier to build libre Svelte apps using Headless UI.",
		"addedOn": "2022-02-26",
		"category": "SvelteKit",
		"tags": ["templates", "ssr", "typescript"]
	},
	{
		"addedOn": "2021-06-24T14:39:28Z",
		"category": "Svelte Add",
		"description": "Add mdsvex to your Svelte project",
		"tags": [],
		"title": "svelte-add/mdsvex",
		"url": "https://github.com/svelte-add/mdsvex"
	},
	{
		"addedOn": "2021-06-24T14:39:29Z",
		"category": "Svelte Add",
		"description": "Add Supabase to your Svelte project",
		"tags": [],
		"title": "supabase-community/svelte-supabase",
		"url": "https://github.com/supabase-community/svelte-supabase"
	},
	{
		"addedOn": "2021-07-21T11:39:29Z",
		"category": "Svelte Add",
		"description": "Add Jest to your SvelteKit project",
		"tags": [],
		"title": "rossyman/svelte-add-jest",
		"url": "https://github.com/rossyman/svelte-add-jest"
	},
	{
		"title": "SvelteKit i18n Template",
		"url": "https://github.com/ivanhofer/typesafe-i18n-demo-sveltekit",
		"description": "A fully working SEO optimized i18n template",
		"npm": "",
		"addedOn": "2021-12-08",
		"category": "SvelteKit",
		"tags": ["blog", "code splitting", "lazy loading", "seo", "ssr", "templates", "typescript"]
	},
	{
		"title": "svelte-ts-tailwind-template",
		"url": "https://github.com/colinbate/svelte-ts-tailwind-template",
		"description": "Svelte app template with TypeScript and TailwindCSS.",
		"npm": "",
		"addedOn": "2022-02-28",
		"category": "Svelte",
		"tags": ["templates", "typescript"]
	},
	{
		"title": "SENT-template",
		"url": "https://github.com/the-homeless-god/SENT-template",
		"description": "Skip setup and start code with SENT (Sapper Express Node Template) and other tools like TypeScript, Linters, Tests, Docker and so on",
		"npm": "",
		"addedOn": "2020-08-01",
		"category": "Svelte",
		"tags": [
			"blog",
			"code splitting",
			"components and libraries",
			"editor tools",
			"integrations",
			"preprocessors",
			"stores and state",
			"webpack",
			"typescript",
			"testing",
			"ssr",
			"storybook",
			"templates",
			"component sets"
		]
	},
	{
		"title": "Yuyutsu",
		"url": "https://github.com/sharu725/yuyutsu",
		"description": "A minimal Sveltekit theme with a sidebar.",
		"npm": "",
		"addedOn": "2022-03-02",
		"category": "SvelteKit",
		"tags": ["blog", "markdown", "templates"]
	},
	{
		"title": "sveltekit-blog-template",
		"url": "https://github.com/K-Sato1995/sveltekit-blog-template",
		"description": "A minimalistic markdown based blog template built with Sveltekit",
		"npm": "",
		"addedOn": "2022-03-09",
		"category": "SvelteKit",
		"tags": ["blog", "templates"]
	},
	{
		"title": "Urara",
		"url": "https://github.com/importantimport/urara",
		"description": "Sweet, Powerful, IndieWeb-Compatible SvelteKit Blog Starter.",
		"npm": "",
		"addedOn": "2022-03-09",
		"category": "SvelteKit",
		"tags": ["blog", "mdsvex", "typescript", "templates"]
	},
	{
		"title": "A Svelte + FAST + Vite starter project",
		"url": "https://github.com/microsoft/fast/tree/master/examples/svelte-starters/svelte-fast-starter",
		"description": "A Svelte + FAST + Vite starter project",
		"npm": "svelte-fast-vite-starter-project",
		"addedOn": "2022-06-27",
		"category": "Svelte",
		"tags": ["templates"]
	},
	{
		"title": "A Svelte + FAST + Vite + TypeScript starter project",
		"url": "https://github.com/microsoft/fast/tree/master/examples/svelte-starters/svelte-fast-typescript-starter",
		"description": "A Svelte + FAST + Vite + TypeScript starter project",
		"npm": "svelte-fast-vite-typescript-starter-project",
		"addedOn": "2022-06-27",
		"category": "Svelte",
		"tags": ["templates"]
	},
	{
		"title": "Swyxkit",
		"url": "https://github.com/swyxio/swyxkit/",
		"description": "An opinionated blog starter for SvelteKit + Tailwind + Netlify. Refreshed for the great SvelteKit refactor of 2022!",
		"npm": "",
		"addedOn": "2022-09-09",
		"category": "SvelteKit",
		"tags": ["blog", "templates", "mdsvex", "markdown"]
	},
	{
		"title": "QWER Blog Starter",
		"url": "https://github.com/kwchang0831/svelte-QWER",
		"description": "Blog Starter built with SvelteKit and Love. 100 Lighthouse, SEO, Post tags and TOC, Atom feed, Sitemap, PWA, image optimisation, Giscus, UnoCSS, typesafe-i18n",
		"npm": "",
		"addedOn": "2022-08-28",
		"category": "SvelteKit",
		"tags": ["blog", "markdown", "templates", "seo", "typescript"]
	},
	{
		"title": "svelte-mpa",
		"url": "https://github.com/kokizzu/svelte-mpa",
		"description": "Multipage Svelte for any backend",
		"npm": "",
		"addedOn": "2022-09-01",
		"category": "Svelte",
		"tags": ["templates", "integrations"]
	}
]
